{"soc":"27-3092","title":"Court Reporters and Simultaneous Captioners","metros":{"1800001":{"name":"Northern Indiana nonmetropolitan area","emp":80,"med":47850,"avg":53180,"hmed":23,"havg":25.57,"p10":38840,"p25":41480,"p75":54150,"p90":78930,"j1k":0.372,"lq":4.54},"1800002":{"name":"Central Indiana nonmetropolitan area","emp":70,"med":46630,"avg":52200,"hmed":22.42,"havg":25.09,"p10":38880,"p25":44670,"p75":55670,"p90":74490,"j1k":0.432,"lq":5.27},"1800003":{"name":"Southern Indiana nonmetropolitan area","emp":100,"med":47030,"avg":57570,"hmed":22.61,"havg":27.68,"p10":38500,"p25":41200,"p75":61470,"p90":96960,"j1k":0.516,"lq":6.3},"2000006":{"name":"Kansas nonmetropolitan area","emp":40,"med":71070,"avg":63040,"hmed":34.17,"havg":30.31,"p10":44760,"p25":51770,"p75":71070,"p90":71070,"j1k":0.093,"lq":1.14},"2700001":{"name":"Northwest Minnesota nonmetropolitan area","emp":30,"med":66360,"avg":69190,"hmed":31.91,"havg":33.26,"p10":55910,"p25":58010,"p75":81430,"p90":81430,"j1k":0.166,"lq":2.03},"4800002":{"name":"North Region of Texas nonmetropolitan area","emp":40,"med":78520,"avg":75490,"hmed":37.75,"havg":36.29,"p10":23450,"p25":53480,"p75":105410,"p90":106410,"j1k":0.136,"lq":1.66},"4800004":{"name":"Hill Country Region of Texas nonmetropolitan area","emp":30,"med":80020,"avg":83700,"hmed":38.47,"havg":40.24,"p10":36100,"p25":71480,"p75":109440,"p90":130270,"j1k":0.177,"lq":2.16}}}