{"soc":"47-4090","title":"Miscellaneous Construction and Related Workers","metros":{"1000005":{"name":"Sussex Delaware nonmetropolitan area","emp":150,"med":42380,"avg":43570,"hmed":20.38,"havg":20.95,"p10":32120,"p25":37120,"p75":46940,"p90":58240,"j1k":1.588,"lq":8.7},"1300001":{"name":"North Georgia nonmetropolitan area","emp":120,"med":37340,"avg":42950,"hmed":17.95,"havg":20.65,"p10":16970,"p25":26830,"p75":65790,"p90":65790,"j1k":0.628,"lq":3.44},"1300002":{"name":"Middle Georgia nonmetropolitan area","emp":50,"med":38400,"avg":42910,"hmed":18.46,"havg":20.63,"p10":28800,"p25":31930,"p75":49240,"p90":65420,"j1k":0.389,"lq":2.13},"1300003":{"name":"East Georgia nonmetropolitan area","emp":40,"med":33970,"avg":35920,"hmed":16.33,"havg":17.27,"p10":21800,"p25":26830,"p75":43020,"p90":67020,"j1k":0.453,"lq":2.48},"1300004":{"name":"South Georgia nonmetropolitan area","emp":110,"med":58860,"avg":53730,"hmed":28.3,"havg":25.83,"p10":33270,"p25":38440,"p75":65790,"p90":65790,"j1k":0.572,"lq":3.13},"1700002":{"name":"West Central Illinois nonmetropolitan area","emp":40,"med":49910,"avg":52710,"hmed":24,"havg":25.34,"p10":35990,"p25":42030,"p75":49910,"p90":78130,"j1k":0.22,"lq":1.21},"2000006":{"name":"Kansas nonmetropolitan area","emp":40,"med":56000,"avg":57350,"hmed":26.92,"havg":27.57,"p10":35050,"p25":41790,"p75":77460,"p90":77470,"j1k":0.117,"lq":0.64},"2200006":{"name":"Southwest Louisiana nonmetropolitan area","emp":40,"med":36830,"avg":44470,"hmed":17.71,"havg":21.38,"p10":31760,"p25":32220,"p75":49780,"p90":65850,"j1k":0.523,"lq":2.87},"2400006":{"name":"Maryland nonmetropolitan area","emp":90,"med":49280,"avg":48140,"hmed":23.69,"havg":23.14,"p10":44530,"p25":48640,"p75":49280,"p90":49280,"j1k":0.821,"lq":4.5},"2900001":{"name":"Central Missouri nonmetropolitan area","emp":40,"med":43630,"avg":44390,"hmed":20.98,"havg":21.34,"p10":41200,"p25":42520,"p75":44840,"p90":50230,"j1k":0.239,"lq":1.31},"2900002":{"name":"North Missouri nonmetropolitan area","emp":70,"med":45090,"avg":45040,"hmed":21.68,"havg":21.65,"p10":37810,"p25":42520,"p75":47860,"p90":47860,"j1k":0.696,"lq":3.81},"2900003":{"name":"Southeast Missouri nonmetropolitan area","emp":120,"med":45090,"avg":44570,"hmed":21.68,"havg":21.43,"p10":37400,"p25":40980,"p75":47930,"p90":47930,"j1k":0.72,"lq":3.95},"3000004":{"name":"West Montana nonmetropolitan area","emp":40,"med":43900,"avg":44780,"hmed":21.11,"havg":21.53,"p10":35880,"p25":35990,"p75":46680,"p90":62350,"j1k":0.501,"lq":2.75},"3500007":{"name":"Eastern New Mexico nonmetropolitan area","med":47160,"avg":49770,"hmed":22.67,"havg":23.93,"p10":35090,"p25":45230,"p75":49930,"p90":67630},"3700001":{"name":"Eastern North Carolina nonmetropolitan area","emp":40,"med":37370,"avg":42360,"hmed":17.97,"havg":20.36,"p10":31660,"p25":32900,"p75":48560,"p90":69910,"j1k":0.14,"lq":0.77},"3700003":{"name":"Western North Carolina nonmetropolitan area","emp":60,"med":43720,"avg":44930,"hmed":21.02,"havg":21.6,"p10":31660,"p25":31660,"p75":55690,"p90":63700,"j1k":0.248,"lq":1.36},"3800006":{"name":"West North Dakota nonmetropolitan area","emp":90,"med":76570,"avg":81750,"hmed":36.81,"havg":39.3,"p10":50600,"p25":63040,"p75":105170,"p90":105180,"j1k":1.084,"lq":5.94},"3900002":{"name":"North Northeastern Ohio nonmetropolitan area (noncontiguous)","emp":40,"med":47040,"avg":53100,"hmed":22.61,"havg":25.53,"p10":38520,"p25":44090,"p75":62800,"p90":75930,"j1k":0.153,"lq":0.84},"3900004":{"name":"Southern Ohio nonmetropolitan area","emp":30,"med":46470,"avg":54940,"hmed":22.34,"havg":26.41,"p10":38480,"p25":41040,"p75":64750,"p90":75930,"j1k":0.193,"lq":1.06},"4800001":{"name":"Northwestern Region of Texas nonmetropolitan area","emp":100,"med":39130,"avg":42440,"hmed":18.81,"havg":20.4,"p10":31660,"p25":31660,"p75":44720,"p90":63310,"j1k":0.506,"lq":2.77},"4800002":{"name":"North Region of Texas nonmetropolitan area","emp":70,"med":40200,"avg":46820,"hmed":19.33,"havg":22.51,"p10":33800,"p25":37990,"p75":49170,"p90":73860,"j1k":0.254,"lq":1.39},"4800003":{"name":"Eastern Region of Texas nonmetropolitan area","emp":40,"med":38980,"avg":43160,"hmed":18.74,"havg":20.75,"p10":33800,"p25":38980,"p75":48000,"p90":55020,"j1k":0.352,"lq":1.93},"5000001":{"name":"Southern Vermont nonmetropolitan area","emp":40,"med":48440,"avg":49340,"hmed":23.29,"havg":23.72,"p10":45410,"p25":46660,"p75":49110,"p90":59030,"j1k":0.492,"lq":2.69},"5000002":{"name":"Northern Vermont nonmetropolitan area","emp":40,"med":47970,"avg":51120,"hmed":23.06,"havg":24.58,"p10":46300,"p25":46430,"p75":56890,"p90":56890,"j1k":0.411,"lq":2.25}}}